hydrodb/__init__.py
hydrodb/hydrodb.py
hydrodb/visuals.py
hydrodb-1.0.9.dist-info/METADATA
hydrodb-1.0.9.dist-info/WHEEL
hydrodb-1.0.9.dist-info/top_level.txt
hydrodb-1.0.9.dist-info/RECORD
